LICENSE.txt
README.md
setup.cfg
setup.py
expp/__init__.py
expp/decl.py
expp.egg-info/PKG-INFO
expp.egg-info/SOURCES.txt
expp.egg-info/dependency_links.txt
expp.egg-info/not-zip-safe
expp.egg-info/top_level.txt